basilearn/__init__.py
basilearn/basilearn.py
basilearn/lesson_controlflow.py
basilearn/lesson_operators.py
basilearn/lesson_variables.py
basilearn/run.py
basilearn-0.1.223.dist-info/LICENSE
basilearn-0.1.223.dist-info/METADATA
basilearn-0.1.223.dist-info/WHEEL
basilearn-0.1.223.dist-info/entry_points.txt
basilearn-0.1.223.dist-info/top_level.txt
basilearn-0.1.223.dist-info/RECORD
