Metadata-Version: 2.1
Name: basilearn
Version: 0.1.223
Summary: A library for educational content and interactive learning
Home-page: 
Author: Barbara Asiamah
Author-email: barbaraasiamah99@gmail.com
Keywords: education,interactive-learning,python,library
Classifier: Programming Language :: Python :: 3
Classifier: License :: OSI Approved :: MIT License
Classifier: Operating System :: OS Independent
Classifier: Topic :: Education
Requires-Python: >=3.7
License-File: LICENSE
Requires-Dist: setuptools>=56.0.0
